aes.py
setup.py
slowaes.egg-info/PKG-INFO
slowaes.egg-info/SOURCES.txt
slowaes.egg-info/dependency_links.txt
slowaes.egg-info/top_level.txt